mlprg/__init__.py
mlprg/mlprg.py
mlprg/prgs.txt
mlprg/prgsl.txt
mlprg-1.0.7.dist-info/LICENSE
mlprg-1.0.7.dist-info/METADATA
mlprg-1.0.7.dist-info/WHEEL
mlprg-1.0.7.dist-info/top_level.txt
mlprg-1.0.7.dist-info/RECORD
